Metadata-Version: 2.1
Name: otda
Version: 0.0.1
Summary: Package for doing optimal transport based domain adaptation.
Author: Luis Carlos Garcia Peraza Herrera
Author-email: luiscarlos.gph@gmail.com
License: MIT
License-File: LICENSE
